scriptize/__init__.py
scriptize/config.py
scriptize/exceptions.py
scriptize/pydantic_tools.py
scriptize/scriptize_db.py
scriptize/api/requests/__init__.py
scriptize-0.0.0.3.dist-info/LICENSE
scriptize-0.0.0.3.dist-info/METADATA
scriptize-0.0.0.3.dist-info/WHEEL
scriptize-0.0.0.3.dist-info/top_level.txt
scriptize-0.0.0.3.dist-info/RECORD
