Metadata-Version: 2.1
Name: scriptize
Version: 0.0.0.3
Summary: Jarvis most recommended script api!
Home-page: https://github.com/tomneto
Author: Elemental Tools - Tom Neto
Author-email: info@tomneto.com
License: MIT
License-File: LICENSE
Requires-Dist: annotated-types (==0.6.0)
Requires-Dist: antiorm (==1.2.1)
Requires-Dist: anyio (==3.7.1)
Requires-Dist: attrs (==23.1.0)
Requires-Dist: certifi (==2023.7.22)
Requires-Dist: cloudant (==2.15.0)
Requires-Dist: exceptiongroup (==1.1.3)
Requires-Dist: fastapi (==0.104.0)
Requires-Dist: greenlet (==3.0.0)
Requires-Dist: h11 (==0.14.0)
Requires-Dist: idna (==3.4)
Requires-Dist: numpy (==1.26.1)
Requires-Dist: outcome (==1.3.0)
Requires-Dist: packaging (==23.2)
Requires-Dist: pandas (==2.1.1)
Requires-Dist: pip (==22.3.1)
Requires-Dist: playwright (==1.39.0)
Requires-Dist: pydantic-core (==2.10.1)
Requires-Dist: pydantic (==2.4.2)
Requires-Dist: pyee (==11.0.1)
Requires-Dist: PySocks (==1.7.1)
Requires-Dist: python-dateutil (==2.8.2)
Requires-Dist: python-dotenv (==1.0.0)
Requires-Dist: pytz (==2023.3.post1)
Requires-Dist: requests (==2.31.0)
Requires-Dist: selenium (==4.14.0)
Requires-Dist: setuptools (==65.5.1)
Requires-Dist: six (==1.16.0)
Requires-Dist: sniffio (==1.3.0)
Requires-Dist: sortedcontainers (==2.4.0)
Requires-Dist: starlette (==0.27.0)
Requires-Dist: trio-websocket (==0.11.1)
Requires-Dist: trio (==0.22.2)
Requires-Dist: typing-extensions (==4.8.0)
Requires-Dist: tzdata (==2023.3)
Requires-Dist: urllib3 (==2.0.7)
Requires-Dist: uvicorn (==0.23.2)
Requires-Dist: webdriver-manager (==4.0.1)
Requires-Dist: wheel (==0.38.4)
Requires-Dist: wsproto (==1.2.0)
Requires-Dist: google-api-python-client
Requires-Dist: google-auth-httplib2
Requires-Dist: google-auth-oauthlib
